az_iranian_bank_gateways-2.3.4.dist-info/licenses/LICENSE
azbankgateways/__init__.py
azbankgateways/admin.py
azbankgateways/apps.py
azbankgateways/bankfactories.py
azbankgateways/bankfactories_interface.py
azbankgateways/default_settings.py
azbankgateways/forms.py
azbankgateways/types.py
azbankgateways/urls.py
azbankgateways/utils.py
azbankgateways/banks/__init__.py
azbankgateways/banks/asanpardakht.py
azbankgateways/banks/bahamta.py
azbankgateways/banks/banks.py
azbankgateways/banks/bmi.py
azbankgateways/banks/irandargah.py
azbankgateways/banks/mellat.py
azbankgateways/banks/sep.py
azbankgateways/banks/zarinpal.py
azbankgateways/banks/zibal.py
azbankgateways/exceptions/__init__.py
azbankgateways/exceptions/exceptions.py
azbankgateways/locale/en/LC_MESSAGES/django.mo
azbankgateways/locale/en/LC_MESSAGES/django.po
azbankgateways/locale/fa/LC_MESSAGES/django.mo
azbankgateways/locale/fa/LC_MESSAGES/django.po
azbankgateways/migrations/0001_initial.py
azbankgateways/migrations/0002_auto_20210102_0721.py
azbankgateways/migrations/0003_bank_bank_choose_identifier.py
azbankgateways/migrations/0004_auto_20211115_1500.py
azbankgateways/migrations/0005_alter_bank_bank_type_alter_bank_created_at_and_more.py
azbankgateways/migrations/0006_alter_bank_bank_type.py
azbankgateways/migrations/__init__.py
azbankgateways/models/__init__.py
azbankgateways/models/banks.py
azbankgateways/models/enum.py
azbankgateways/readers/__init__.py
azbankgateways/readers/bases.py
azbankgateways/readers/defaults.py
azbankgateways/templates/azbankgateways/redirect_to_bank.html
azbankgateways/templates/azbankgateways/samples/base.html
azbankgateways/templates/azbankgateways/samples/base_site.html
azbankgateways/templates/azbankgateways/samples/gateway.html
azbankgateways/templates/azbankgateways/samples/result.html
azbankgateways/views/__init__.py
azbankgateways/views/banks.py
azbankgateways/views/samples.py
az_iranian_bank_gateways-2.3.4.dist-info/METADATA
az_iranian_bank_gateways-2.3.4.dist-info/WHEEL
az_iranian_bank_gateways-2.3.4.dist-info/top_level.txt
az_iranian_bank_gateways-2.3.4.dist-info/RECORD
